logexp/__init__.py
logexp/error.py
logexp/executor.py
logexp/experiment.py
logexp/logstore.py
logexp/params.py
logexp/report.py
logexp/settings.py
logexp/storage.py
logexp/version.py
logexp/worker.py
logexp/cli/__init__.py
logexp/cli/delete.py
logexp/cli/init.py
logexp/cli/list.py
logexp/cli/logs.py
logexp/cli/note.py
logexp/cli/params.py
logexp/cli/prune.py
logexp/cli/rename.py
logexp/cli/run.py
logexp/cli/show.py
logexp/cli/subcommand.py
logexp/metadata/__init__.py
logexp/metadata/git.py
logexp/metadata/platform.py
logexp/metadata/runinfo.py
logexp/metadata/status.py
logexp/utils/__init__.py
logexp/utils/capture.py
logexp/utils/editor.py
logexp/utils/jsondict.py
logexp/utils/submodule.py
logexp/utils/table.py
logexp-0.1.3.dist-info/LICENSE
logexp-0.1.3.dist-info/METADATA
logexp-0.1.3.dist-info/WHEEL
logexp-0.1.3.dist-info/entry_points.txt
logexp-0.1.3.dist-info/top_level.txt
logexp-0.1.3.dist-info/RECORD
