Metadata-Version: 2.1
Name: logexp
Version: 0.1.3
Summary: simple experiment manager for machine learning.
Home-page: https://github.com/altescy/logexp
Author: altescy
Author-email: altescy@fastmail.com
License: MIT License
Keywords: machine learning experiment manager
Platform: UNKNOWN
Classifier: Intended Audience :: Science/Research
Classifier: Development Status :: 3 - Alpha
Classifier: License :: OSI Approved :: MIT License
Classifier: Programming Language :: Python :: 3.7
Classifier: Topic :: Scientific/Engineering :: Artificial Intelligence
Requires-Python: >=3.7.3
